FPGA/comunication.sv
`timescale 1ns / 1ps

module comunication #(
    parameter int unsigned clock_max = 25_000_000
)(
    input logic clk_25mhz,
    input logic sclk_in, //clock vindo do pico
    input logic mosi_in, //input data from pico 
    input logic active,
    input logic reset,

    output logic data_ready,
    output logic [15:0] audio_out  //testar se pacotes de 16 bits fazem uma transnmissão lisa
);

// Use explicit localparam-based states to avoid Yosys enum handling issues
localparam logic [1:0] IDLE      = 2'd0;
localparam logic [1:0] RECEIVING = 2'd1;

logic [1:0] state;      
logic [15:0] shift_reg; 
logic [3:0]  bit_counter;

logic sclk_d1, sclk_d2; 

//tornando o clock do pico um clock conhecido pelo fpga
always_ff @(posedge clk_25mhz) begin 
        sclk_d1 <= sclk_in;
        sclk_d2 <= sclk_d1;
end 

logic sclk_posedge;  //por algum motivo não funcionou quando criei e atribui junto
assign sclk_posedge = (sclk_d1 == 1'b1) && (sclk_d2 == 1'b0);

always_ff @(posedge clk_25mhz or posedge reset)
    begin
        if(reset == 1'b1) begin  //implementação do botão de desligar ou desativar comunicação
            state <= IDLE;
            shift_reg <= 16'b0000000000000000;
            bit_counter <= 4'b0000;
            data_ready <= 1'b0;
            audio_out <= 16'b0000000000000000;
        

        end else begin //a cada pulso de clock do pico, executar
            if (data_ready == 1'b1) begin
                data_ready <= 1'b0;
            end

            case(state)
                IDLE: begin //modo ociosos, sem novos dados chegando
                    if(active == 1'b1) begin
                        state <= RECEIVING;
                        shift_reg <= 16'b0000000000000000;
                        bit_counter <= 4'b0000;
                    end
                end  

                RECEIVING: begin //estado em que a comunicação está acontecendo, recebendo dados do pico
                    if(active == 1'b0) begin
                        state <= IDLE;
                        
                    end else if (sclk_posedge) begin
                        shift_reg <= {shift_reg[14:0], mosi_in};

                        if(bit_counter == 4'd15) begin
                            audio_out <= {shift_reg[14:0], mosi_in};
                            state <= RECEIVING;
                            data_ready <= 1'b1;
                            bit_counter <= 4'b0000;

                        end else begin
                            bit_counter <= bit_counter + 1'b1;
                        end
                    end
                end 

            endcase
        end 
    end 
endmodule

FPGA/tb_comunication.sv
`timescale 1ns / 1ps

// Módulo de Testbench
// Não tem entradas nem saídas
module tb_comunication;

    // --- 1. Constantes para os Clocks ---
    // Clock principal de 25MHz (Período = 1 / 25MHz = 40 ns)
    localparam int CLK_PERIOD = 40; 
    
    // Clock do SPI (SCLK) de 2MHz (Período = 500 ns)
    // (1 / (16 * 20kHz)) = 3.125us (mínimo)
    // (1 / 2MHz) = 500ns (muito mais rápido, ótimo)
    localparam int SCLK_PERIOD = 500; 

    // --- 2. Sinais do Testbench ---
    // Entradas para o DUT
    logic        tb_clk;
    logic        sclk_in;
    logic        mosi_in;
    logic        active;
    logic        reset;


    // Saídas do DUT
    wire [15:0] audio_out;
    wire        data_ready;


    // --- 3. Instanciar o Módulo (DUT) ---
    // Conecta os sinais do testbench às portas do módulo
    comunication dut (
        .clk_25mhz  (tb_clk),
        
        .sclk_in   (sclk_in),
        .mosi_in   (mosi_in),
        .active    (active),
        .reset     (reset),
        .audio_out (audio_out),
        .data_ready(data_ready)
    );

    // --- 4. Gerador de Clock Principal (25MHz) ---
    initial begin
        tb_clk = 0;
        // 'forever' cria um loop infinito que gera o clock
        forever #(CLK_PERIOD / 2) tb_clk = ~tb_clk;
    end

    // --- 5. Tarefa (Task) para simular o Pico enviando 16 bits ---
    // Uma 'task' é como uma função para simulação
    task send_spi_word(input [15:0] data_word);
        // Espera o próximo ciclo de clock para sincronizar
        @(posedge tb_clk);
        
        // Ativa o "Chip Select" (ativo-alto, como no seu código)
        active <= 1'b1; 
        sclk_in <= 1'b0;
        
        // Espera alguns ciclos para o DUT ver o 'active'
        #(CLK_PERIOD * 2); 

        // Loop para enviar os 16 bits, do mais significativo (MSB) ao menos (LSB)
        for (int i = 15; i >= 0; i--) begin
            
            // Coloca o bit de dado na linha
            mosi_in <= data_word[i];
            
            // Espera meio período do SCLK
            #(SCLK_PERIOD / 2);
            
            // Sobe o SCLK (o DUT captura o dado aqui)
            sclk_in <= 1'b1;
            
            // Espera meio período do SCLK
            #(SCLK_PERIOD / 2);
            
            // Desce o SCLK
            sclk_in <= 1'b0;
        end
        
        // Espera um pouco antes de desativar
        #(CLK_PERIOD * 2);
        active <= 1'b0; // Desativa o "Chip Select"
    endtask


    // --- 6. Sequência de Teste Principal ---
    initial begin
        // Abre o arquivo de formas de onda (opcional, mas recomendado)
        $dumpfile("dump.vcd");
        $dumpvars(0, tb_comunication);

        // Inicia a simulação com o reset ativado
        $display("Iniciando simulação... Reset ativado.");
        reset     <= 1'b1;
        active    <= 1'b0;
        sclk_in   <= 1'b0;
        mosi_in   <= 1'b0;
        #100ns; // Espera 100 ns

        // Libera o reset
        reset <= 1'b0;
        $display("Reset liberado. Módulo em IDLE.");
        @(posedge tb_clk);
        
        $display("TESTE 1: Enviando 16'hA5A5...");
    
    // 'fork' inicia um bloco paralelo
    fork
        // 'join_none' diz: não espere esta tarefa terminar,
        // continue executando o código principal.
        send_spi_word(16'hA5A5);
    join_none

    // AGORA, o 'send_spi_word' está rodando em paralelo,
    // e esta linha @(posedge) está escutando AO MESMO TEMPO.
    @(posedge data_ready);
    $display("... Pulso 'data_ready' recebido!");
    $display("... Valor em 'audio_out' = %h", audio_out);

    // O resto da sua lógica de assert estava correta
    assert (audio_out == 16'hA5A5)
        else $error("FALHA TESTE 1: Valor esperado era A5A5, mas foi %h", audio_out);

    @(posedge tb_clk);
    assert (data_ready == 1'b0)
        else $error("FALHA TESTE 1: 'data_ready' não voltou para 0!");

    $display("TESTE 1: Concluído com sucesso!");
    
    #(SCLK_PERIOD * 4);

    // --- TESTE 2: CORRIGIDO COM FORK...JOIN_NONE ---
    $display("TESTE 2: Enviando 16'hBEEF...");
    
    fork
        send_spi_word(16'hBEEF);
    join_none
    
    @(posedge data_ready);
    $display("... Pulso 'data_ready' recebido!");
    $display("... Valor em 'audio_out' = %h", audio_out);
    
    assert (audio_out == 16'hBEEF)
        else $error("FALHA TESTE 2: Valor esperado era BEEF, mas foi %h", audio_out);
    
    $display("TESTE 2: Concluído com sucesso!");
    
    #1000ns;
    $display("Simulação concluída.");
    $finish;
    end

endmodule

FPGA/dump.vcd
$date
	Tue Oct 28 07:36:59 2025
$end
$version
	Icarus Verilog
$end
$timescale
	1ps
$end
$scope module tb_comunication $end
$var wire 1 ! data_ready $end
$var wire 16 " audio_out [15:0] $end
$var parameter 32 # CLK_PERIOD $end
$var parameter 32 $ SCLK_PERIOD $end
$var reg 1 % active $end
$var reg 1 & mosi_in $end
$var reg 1 ' reset $end
$var reg 1 ( sclk_in $end
$var reg 1 ) tb_clk $end
$scope module dut $end
$var wire 1 % active $end
$var wire 1 ) clk_25mhz $end
$var wire 1 & mosi_in $end
$var wire 1 ' reset $end
$var wire 1 ( sclk_in $end
$var wire 1 * sclk_posedge $end
$var parameter 2 + IDLE $end
$var parameter 2 , RECEIVING $end
$var parameter 32 - clock_max $end
$var reg 16 . audio_out [15:0] $end
$var reg 4 / bit_counter [3:0] $end
$var reg 1 ! data_ready $end
$var reg 1 0 sclk_d1 $end
$var reg 1 1 sclk_d2 $end
$var reg 16 2 shift_reg [15:0] $end
$var reg 2 3 state [1:0] $end
$upscope $end
$scope task send_spi_word $end
$var reg 16 4 data_word [15:0] $end
$scope begin $ivl_for_loop0 $end
$var integer 32 5 i [31:0] $end
$upscope $end
$upscope $end
$upscope $end
$enddefinitions $end
$comment Show the parameter values. $end
$dumpall
b1011111010111100001000000 -
b1 ,
b0 +
b111110100 $
b101000 #
$end
#0
$dumpvars
b0 5
bx 4
b0 3
b0 2
x1
x0
b0 /
b0 .
x*
0)
0(
1'
0&
0%
b0 "
0!
$end
#20000
0*
00
1)
#40000
0)
#60000
01
1)
#80000
0)
#100000
0'
b1010010110100101 4
1)
#120000
0)
#140000
1%
1)
#160000
0)
#180000
b1 3
1)
#200000
0)
#220000
1&
1)
b1111 5
#240000
0)
#260000
1)
#280000
0)
#300000
1)
#320000
0)
#340000
1)
#360000
0)
#380000
1)
#400000
0)
#420000
1)
#440000
0)
#460000
1)
#470000
1(
#480000
0)
#500000
1*
10
1)
#520000
0)
#540000
0*
b1 /
b1 2
11
1)
#560000
0)
#580000
1)
#600000
0)
#620000
1)
#640000
0)
#660000
1)
#680000
0)
#700000
1)
#720000
0&
0(
0)
b1110 5
#740000
00
1)
#760000
0)
#780000
01
1)
#800000
0)
#820000
1)
#840000
0)
#860000
1)
#880000
0)
#900000
1)
#920000
0)
#940000
1)
#960000
0)
#970000
1(
#980000
1*
10
1)
#1000000
0)
#1020000
0*
b10 /
b10 2
11
1)
#1040000
0)
#1060000
1)
#1080000
0)
#1100000
1)
#1120000
0)
#1140000
1)
#1160000
0)
#1180000
1)
#1200000
0)
#1220000
1&
0(
1)
b1101 5
#1240000
0)
#1260000
00
1)
#1280000
0)
#1300000
01
1)
#1320000
0)
#1340000
1)
#1360000
0)
#1380000
1)
#1400000
0)
#1420000
1)
#1440000
0)
#1460000
1)
#1470000
1(
#1480000
0)
#1500000
1*
10
1)
#1520000
0)
#1540000
0*
b11 /
b101 2
11
1)
#1560000
0)
#1580000
1)
#1600000
0)
#1620000
1)
#1640000
0)
#1660000
1)
#1680000
0)
#1700000
1)
#1720000
0&
0(
0)
b1100 5
#1740000
00
1)
#1760000
0)
#1780000
01
1)
#1800000
0)
#1820000
1)
#1840000
0)
#1860000
1)
#1880000
0)
#1900000
1)
#1920000
0)
#1940000
1)
#1960000
0)
#1970000
1(
#1980000
1*
10
1)
#2000000
0)
#2020000
0*
b100 /
b1010 2
11
1)
#2040000
0)
#2060000
1)
#2080000
0)
#2100000
1)
#2120000
0)
#2140000
1)
#2160000
0)
#2180000
1)
#2200000
0)
#2220000
0(
1)
b1011 5
#2240000
0)
#2260000
00
1)
#2280000
0)
#2300000
01
1)
#2320000
0)
#2340000
1)
#2360000
0)
#2380000
1)
#2400000
0)
#2420000
1)
#2440000
0)
#2460000
1)
#2470000
1(
#2480000
0)
#2500000
1*
10
1)
#2520000
0)
#2540000
0*
b101 /
b10100 2
11
1)
#2560000
0)
#2580000
1)
#2600000
0)
#2620000
1)
#2640000
0)
#2660000
1)
#2680000
0)
#2700000
1)
#2720000
1&
0(
0)
b1010 5
#2740000
00
1)
#2760000
0)
#2780000
01
1)
#2800000
0)
#2820000
1)
#2840000
0)
#2860000
1)
#2880000
0)
#2900000
1)
#2920000
0)
#2940000
1)
#2960000
0)
#2970000
1(
#2980000
1*
10
1)
#3000000
0)
#3020000
0*
b110 /
b101001 2
11
1)
#3040000
0)
#3060000
1)
#3080000
0)
#3100000
1)
#3120000
0)
#3140000
1)
#3160000
0)
#3180000
1)
#3200000
0)
#3220000
0&
0(
1)
b1001 5
#3240000
0)
#3260000
00
1)
#3280000
0)
#3300000
01
1)
#3320000
0)
#3340000
1)
#3360000
0)
#3380000
1)
#3400000
0)
#3420000
1)
#3440000
0)
#3460000
1)
#3470000
1(
#3480000
0)
#3500000
1*
10
1)
#3520000
0)
#3540000
0*
b111 /
b1010010 2
11
1)
#3560000
0)
#3580000
1)
#3600000
0)
#3620000
1)
#3640000
0)
#3660000
1)
#3680000
0)
#3700000
1)
#3720000
1&
0(
0)
b1000 5
#3740000
00
1)
#3760000
0)
#3780000
01
1)
#3800000
0)
#3820000
1)
#3840000
0)
#3860000
1)
#3880000
0)
#3900000
1)
#3920000
0)
#3940000
1)
#3960000
0)
#3970000
1(
#3980000
1*
10
1)
#4000000
0)
#4020000
0*
b1000 /
b10100101 2
11
1)
#4040000
0)
#4060000
1)
#4080000
0)
#4100000
1)
#4120000
0)
#4140000
1)
#4160000
0)
#4180000
1)
#4200000
0)
#4220000
0(
1)
b111 5
#4240000
0)
#4260000
00
1)
#4280000
0)
#4300000
01
1)
#4320000
0)
#4340000
1)
#4360000
0)
#4380000
1)
#4400000
0)
#4420000
1)
#4440000
0)
#4460000
1)
#4470000
1(
#4480000
0)
#4500000
1*
10
1)
#4520000
0)
#4540000
0*
b1001 /
b101001011 2
11
1)
#4560000
0)
#4580000
1)
#4600000
0)
#4620000
1)
#4640000
0)
#4660000
1)
#4680000
0)
#4700000
1)
#4720000
0&
0(
0)
b110 5
#4740000
00
1)
#4760000
0)
#4780000
01
1)
#4800000
0)
#4820000
1)
#4840000
0)
#4860000
1)
#4880000
0)
#4900000
1)
#4920000
0)
#4940000
1)
#4960000
0)
#4970000
1(
#4980000
1*
10
1)
#5000000
0)
#5020000
0*
b1010 /
b1010010110 2
11
1)
#5040000
0)
#5060000
1)
#5080000
0)
#5100000
1)
#5120000
0)
#5140000
1)
#5160000
0)
#5180000
1)
#5200000
0)
#5220000
1&
0(
1)
b101 5
#5240000
0)
#5260000
00
1)
#5280000
0)
#5300000
01
1)
#5320000
0)
#5340000
1)
#5360000
0)
#5380000
1)
#5400000
0)
#5420000
1)
#5440000
0)
#5460000
1)
#5470000
1(
#5480000
0)
#5500000
1*
10
1)
#5520000
0)
#5540000
0*
b1011 /
b10100101101 2
11
1)
#5560000
0)
#5580000
1)
#5600000
0)
#5620000
1)
#5640000
0)
#5660000
1)
#5680000
0)
#5700000
1)
#5720000
0&
0(
0)
b100 5
#5740000
00
1)
#5760000
0)
#5780000
01
1)
#5800000
0)
#5820000
1)
#5840000
0)
#5860000
1)
#5880000
0)
#5900000
1)
#5920000
0)
#5940000
1)
#5960000
0)
#5970000
1(
#5980000
1*
10
1)
#6000000
0)
#6020000
0*
b1100 /
b101001011010 2
11
1)
#6040000
0)
#6060000
1)
#6080000
0)
#6100000
1)
#6120000
0)
#6140000
1)
#6160000
0)
#6180000
1)
#6200000
0)
#6220000
0(
1)
b11 5
#6240000
0)
#6260000
00
1)
#6280000
0)
#6300000
01
1)
#6320000
0)
#6340000
1)
#6360000
0)
#6380000
1)
#6400000
0)
#6420000
1)
#6440000
0)
#6460000
1)
#6470000
1(
#6480000
0)
#6500000
1*
10
1)
#6520000
0)
#6540000
0*
b1101 /
b1010010110100 2
11
1)
#6560000
0)
#6580000
1)
#6600000
0)
#6620000
1)
#6640000
0)
#6660000
1)
#6680000
0)
#6700000
1)
#6720000
1&
0(
0)
b10 5
#6740000
00
1)
#6760000
0)
#6780000
01
1)
#6800000
0)
#6820000
1)
#6840000
0)
#6860000
1)
#6880000
0)
#6900000
1)
#6920000
0)
#6940000
1)
#6960000
0)
#6970000
1(
#6980000
1*
10
1)
#7000000
0)
#7020000
0*
b1110 /
b10100101101001 2
11
1)
#7040000
0)
#7060000
1)
#7080000
0)
#7100000
1)
#7120000
0)
#7140000
1)
#7160000
0)
#7180000
1)
#7200000
0)
#7220000
0&
0(
1)
b1 5
#7240000
0)
#7260000
00
1)
#7280000
0)
#7300000
01
1)
#7320000
0)
#7340000
1)
#7360000
0)
#7380000
1)
#7400000
0)
#7420000
1)
#7440000
0)
#7460000
1)
#7470000
1(
#7480000
0)
#7500000
1*
10
1)
#7520000
0)
#7540000
0*
b1111 /
b101001011010010 2
11
1)
#7560000
0)
#7580000
1)
#7600000
0)
#7620000
1)
#7640000
0)
#7660000
1)
#7680000
0)
#7700000
1)
#7720000
1&
0(
0)
b0 5
#7740000
00
1)
#7760000
0)
#7780000
01
1)
#7800000
0)
#7820000
1)
#7840000
0)
#7860000
1)
#7880000
0)
#7900000
1)
#7920000
0)
#7940000
1)
#7960000
0)
#7970000
1(
#7980000
1*
10
1)
#8000000
0)
#8020000
0*
b0 /
1!
b1010010110100101 "
b1010010110100101 .
b1010010110100101 2
11
1)
#8040000
0)
#8060000
0!
1)
#8080000
0)
#8100000
1)
#8120000
0)
#8140000
1)
#8160000
0)
#8180000
1)
#8200000
0)
#8220000
0(
1)
b11111111111111111111111111111111 5
#8240000
0)
#8260000
00
1)
#8280000
0)
#8300000
01
0%
1)
#8320000
0)
#8340000
b0 3
1)
